AllGitStatus/Impl/GetRepositoriesModal.py
AllGitStatus/Impl/__init__.py
AllGitStatus/Lib.py
AllGitStatus/MainApp.py
AllGitStatus/MainApp.tcss
AllGitStatus/__init__.py
AllGitStatus/__main__.py
AllGitStatus/py.typed
allgitstatus-0.6.3.dist-info/WHEEL
allgitstatus-0.6.3.dist-info/entry_points.txt
allgitstatus-0.6.3.dist-info/METADATA
allgitstatus-0.6.3.dist-info/RECORD
