Metadata-Version: 2.3
Name: allgitstatus
Version: 0.6.3
Summary: Checks the git status for all repositories found under the specified directory.
Author: David Brownell
Author-email: David Brownell <github@davidbrownell.com>
License: MIT
Classifier: Operating System :: MacOS
Classifier: Operating System :: Microsoft :: Windows
Classifier: Operating System :: POSIX :: Linux
Classifier: Programming Language :: Python
Classifier: Programming Language :: Python :: 3.13
Requires-Dist: attrs>=25.3.0
Requires-Dist: dbrownell-common>=0.16.0
Requires-Dist: textual>=5.3.0
Requires-Dist: typer>=0.16.1
Requires-Python: >=3.13
Project-URL: Documentation, https://github.com/davidbrownell/AllGitStatus
Project-URL: Homepage, https://github.com/davidbrownell/AllGitStatus
Project-URL: Repository, https://github.com/davidbrownell/AllGitStatus
